[
    {
        "title": "Test Title",
        "text": "Test text",
        "id": "test_id1"
    },
    {
        "title": "Note Title",
        "text": "Note Text",
        "id": "test_id2"
    },
    {
        "title": "Reminder",
        "text": "Take out trash and recycling",
        "id": "test_id3"
    },
    {
        "title": "test",
        "text": "1234",
        "id": 12345
    },
    {
        "title": "test2",
        "text": "yada",
        "id": "41tdog8b8kdwqj3cf"
    },
    {
        "title": "asdf",
        "text": "asdf",
        "id": "41tdog8b8kdwqkzud"
    },
    {
        "title": "test5",
        "text": "five",
        "id": "41tdogakjkdwrpe7l"
    }
]